dropbox_test_api_bearer_token/__init__.py
dropbox_test_api_bearer_token/api_helper.py
dropbox_test_api_bearer_token/configuration.py
dropbox_test_api_bearer_token/decorators.py
dropbox_test_api_bearer_token/dropbox_test_api_bearer_token_client.py
dropbox_test_api_bearer_token/controllers/__init__.py
dropbox_test_api_bearer_token/controllers/base_controller.py
dropbox_test_api_bearer_token/controllers/files_controller.py
dropbox_test_api_bearer_token/exceptions/__init__.py
dropbox_test_api_bearer_token/exceptions/api_exception.py
dropbox_test_api_bearer_token/http/__init__.py
dropbox_test_api_bearer_token/http/http_call_back.py
dropbox_test_api_bearer_token/http/http_client.py
dropbox_test_api_bearer_token/http/http_context.py
dropbox_test_api_bearer_token/http/http_method_enum.py
dropbox_test_api_bearer_token/http/http_request.py
dropbox_test_api_bearer_token/http/http_response.py
dropbox_test_api_bearer_token/http/requests_client.py
dropbox_test_api_bearer_token/http/auth/__init__.py
dropbox_test_api_bearer_token/http/auth/o_auth_2.py
dropbox_test_api_bearer_token/models/__init__.py
dropbox_test_api_bearer_token/models/response.py
dropbox_test_api_bearer_token-1.0.dist-info/LICENSE
dropbox_test_api_bearer_token-1.0.dist-info/METADATA
dropbox_test_api_bearer_token-1.0.dist-info/WHEEL
dropbox_test_api_bearer_token-1.0.dist-info/top_level.txt
dropbox_test_api_bearer_token-1.0.dist-info/RECORD
